README
setup.py
wayround_org/utils/Makefile.py
wayround_org/utils/__init__.py
wayround_org/utils/archive.py
wayround_org/utils/autohtml.py
wayround_org/utils/bottle.py
wayround_org/utils/checksum.py
wayround_org/utils/class_applicator.py
wayround_org/utils/config.sub
wayround_org/utils/crypto.py
wayround_org/utils/cython.py
wayround_org/utils/data_cache.py
wayround_org/utils/data_cache_miscs.py
wayround_org/utils/datetime_iso8601.py
wayround_org/utils/datetime_rfc3501.py
wayround_org/utils/datetime_rfc5322.py
wayround_org/utils/db.py
wayround_org/utils/dict.py
wayround_org/utils/directory.py
wayround_org/utils/domain.py
wayround_org/utils/edit.py
wayround_org/utils/error.py
wayround_org/utils/exec.py
wayround_org/utils/factory.py
wayround_org/utils/file.py
wayround_org/utils/fileindex.py
wayround_org/utils/filter.py
wayround_org/utils/flagged_file.py
wayround_org/utils/ftpwalk.py
wayround_org/utils/getopt.py
wayround_org/utils/gst.py
wayround_org/utils/gtk.py
wayround_org/utils/helprenderer.py
wayround_org/utils/htmlwalk.py
wayround_org/utils/htmlwalk_old.py
wayround_org/utils/http.py
wayround_org/utils/list.py
wayround_org/utils/log.py
wayround_org/utils/logging.py
wayround_org/utils/lxml.py
wayround_org/utils/mako_filters.py
wayround_org/utils/osutils.py
wayround_org/utils/path.py
wayround_org/utils/pkgconfig.py
wayround_org/utils/pm.py
wayround_org/utils/program.py
wayround_org/utils/range.py
wayround_org/utils/shlex.py
wayround_org/utils/socket.py
wayround_org/utils/sqlalchemy.py
wayround_org/utils/stream.py
wayround_org/utils/system_type.py
wayround_org/utils/tag.py
wayround_org/utils/tarball.py
wayround_org/utils/terminal.py
wayround_org/utils/text.py
wayround_org/utils/threading.py
wayround_org/utils/time.py
wayround_org/utils/timer.py
wayround_org/utils/types.py
wayround_org/utils/types_presets.py
wayround_org/utils/uri.py
wayround_org/utils/uri_old.py
wayround_org/utils/uri_std.py
wayround_org/utils/version.py
wayround_org/utils/weakref.py
wayround_org_utils.egg-info/PKG-INFO
wayround_org_utils.egg-info/SOURCES.txt
wayround_org_utils.egg-info/dependency_links.txt
wayround_org_utils.egg-info/requires.txt
wayround_org_utils.egg-info/top_level.txt