Metadata-Version: 1.1
Name: wayround-org-utils
Version: 1.14
Summary: Various service modules
Home-page: https://github.com/AnimusPEXUS/wayround_org_utils
Author: Alexey Gorshkov
Author-email: animus@wayround.org
License: UNKNOWN
Platform: UNKNOWN
Classifier: License :: OSI Approved :: GNU General Public License v3 or later (GPLv3+)
Classifier: Operating System :: POSIX
